animelyrics.py
animelyrics/__init__.py
animelyrics/animelyrics.py
animelyrics-0.1.0.dist-info/LICENSE
animelyrics-0.1.0.dist-info/METADATA
animelyrics-0.1.0.dist-info/WHEEL
animelyrics-0.1.0.dist-info/top_level.txt
animelyrics-0.1.0.dist-info/RECORD
