Metadata-Version: 2.1
Name: animelyrics
Version: 0.1.0
Summary: Library to extract song lyrics from www.animelyrics.com
Home-page: https://github.com/colorfusion/animelyrics
Author: Melvin Yeo
Author-email: melvinyzw@gmail.com
License: MIT
Platform: UNKNOWN
Classifier: License :: OSI Approved :: MIT License
Classifier: Intended Audience :: Developers
Classifier: Development Status :: 5 - Production/Stable
Classifier: Programming Language :: Python
Classifier: Programming Language :: Python :: 3
Classifier: Programming Language :: Python :: 3.5
Classifier: Programming Language :: Python :: 3.6
Classifier: Programming Language :: Python :: 3.7
Classifier: Topic :: Internet :: WWW/HTTP :: Indexing/Search
Classifier: Topic :: Software Development :: Libraries :: Python Modules
Classifier: Topic :: Text Processing :: General
Requires-Python: >=3.0.0
Requires-Dist: requests
Requires-Dist: google
Requires-Dist: beautifulsoup4
Requires-Dist: lxml
